insights4ci/client/__init__.py
insights4ci/client/api.py
python_insights4ci_client-0.0.1.dist-info/LICENSE
python_insights4ci_client-0.0.1.dist-info/METADATA
python_insights4ci_client-0.0.1.dist-info/WHEEL
python_insights4ci_client-0.0.1.dist-info/top_level.txt
python_insights4ci_client-0.0.1.dist-info/RECORD
